CHANGES.rst
DESCRIPTION.rst
LICENSE
MANIFEST.in
README.md
setup.py
src/wai.annotations.voc.egg-info/PKG-INFO
src/wai.annotations.voc.egg-info/SOURCES.txt
src/wai.annotations.voc.egg-info/dependency_links.txt
src/wai.annotations.voc.egg-info/entry_points.txt
src/wai.annotations.voc.egg-info/namespace_packages.txt
src/wai.annotations.voc.egg-info/requires.txt
src/wai.annotations.voc.egg-info/top_level.txt
src/wai/annotations/voc/__init__.py
src/wai/annotations/voc/od/__init__.py
src/wai/annotations/voc/od/_format.py
src/wai/annotations/voc/od/component/_FromVOCOD.py
src/wai/annotations/voc/od/component/_ToVOCOD.py
src/wai/annotations/voc/od/component/_VOCODReader.py
src/wai/annotations/voc/od/component/_VOCODWriter.py
src/wai/annotations/voc/od/component/__init__.py
src/wai/annotations/voc/od/specifier/_VOCODInputFormatSpecifier.py
src/wai/annotations/voc/od/specifier/_VOCODOutputFormatSpecifier.py
src/wai/annotations/voc/od/specifier/__init__.py